odoo/addons/fieldservice_sale_recurring/README.rst
odoo/addons/fieldservice_sale_recurring/__init__.py
odoo/addons/fieldservice_sale_recurring/__manifest__.py
odoo/addons/fieldservice_sale_recurring/i18n/de.po
odoo/addons/fieldservice_sale_recurring/i18n/es.po
odoo/addons/fieldservice_sale_recurring/i18n/es_CL.po
odoo/addons/fieldservice_sale_recurring/i18n/fieldservice_sale_recurring.pot
odoo/addons/fieldservice_sale_recurring/i18n/it.po
odoo/addons/fieldservice_sale_recurring/i18n/pt_BR.po
odoo/addons/fieldservice_sale_recurring/models/__init__.py
odoo/addons/fieldservice_sale_recurring/models/fsm_recurring.py
odoo/addons/fieldservice_sale_recurring/models/product_template.py
odoo/addons/fieldservice_sale_recurring/models/sale_order.py
odoo/addons/fieldservice_sale_recurring/models/sale_order_line.py
odoo/addons/fieldservice_sale_recurring/readme/CONFIGURE.rst
odoo/addons/fieldservice_sale_recurring/readme/CONTRIBUTORS.rst
odoo/addons/fieldservice_sale_recurring/readme/DESCRIPTION.rst
odoo/addons/fieldservice_sale_recurring/readme/INSTALL.rst
odoo/addons/fieldservice_sale_recurring/readme/ROADMAP.rst
odoo/addons/fieldservice_sale_recurring/readme/USAGE.rst
odoo/addons/fieldservice_sale_recurring/security/ir.model.access.csv
odoo/addons/fieldservice_sale_recurring/static/description/icon.png
odoo/addons/fieldservice_sale_recurring/static/description/index.html
odoo/addons/fieldservice_sale_recurring/views/fsm_recurring.xml
odoo/addons/fieldservice_sale_recurring/views/product_template.xml
odoo/addons/fieldservice_sale_recurring/views/sale_order.xml
odoo13_addon_fieldservice_sale_recurring-13.0.1.0.1.dev4.dist-info/METADATA
odoo13_addon_fieldservice_sale_recurring-13.0.1.0.1.dev4.dist-info/WHEEL
odoo13_addon_fieldservice_sale_recurring-13.0.1.0.1.dev4.dist-info/top_level.txt
odoo13_addon_fieldservice_sale_recurring-13.0.1.0.1.dev4.dist-info/RECORD
