Metadata-Version: 2.1
Name: odoo13-addon-fieldservice-sale-recurring
Version: 13.0.1.0.1.dev4
Summary: Sell recurring field services.
Home-page: https://github.com/OCA/field-service
Author: Open Source Integrators, Odoo Community Association (OCA)
Author-email: support@odoo-community.org
License: AGPL-3
Platform: UNKNOWN
Classifier: Programming Language :: Python
Classifier: Framework :: Odoo
Classifier: Framework :: Odoo :: 13.0
Classifier: License :: OSI Approved :: GNU Affero General Public License v3
Classifier: Development Status :: 4 - Beta
Requires-Python: >=3.5
Requires-Dist: odoo13-addon-fieldservice-recurring
Requires-Dist: odoo13-addon-fieldservice-sale
Requires-Dist: odoo <13.1dev,>=13.0a
